src/securepickle/__init__.py
src/securepickle/securepickle.py
secure_pickle-0.0.9.dist-info/METADATA
secure_pickle-0.0.9.dist-info/WHEEL
secure_pickle-0.0.9.dist-info/licenses/LICENSE
secure_pickle-0.0.9.dist-info/RECORD
