Metadata-Version: 2.1
Name: secure-pickle
Version: 0.0.9
Summary: A small package which can add HMACs to pickle files for integrity checks upon unpickling
Project-URL: Homepage, https://github.com/Ethan-Dowalter/secure-pickle-files
Project-URL: Bug Tracker, https://github.com/Ethan-Dowalter/secure-pickle-files/issues
Author-email: Ethan Dowalter <edowalte@uwyo.edu>
License-File: LICENSE
Classifier: License :: OSI Approved :: MIT License
Classifier: Operating System :: OS Independent
Classifier: Programming Language :: Python :: 3
Requires-Python: >=3.7
